DALI/Annotations.py
DALI/__init__.py
DALI/download.py
DALI/extra.py
DALI/main.py
DALI/utilities.py
DALI/vizualization.py
DALI/files/template.xml
DALI_dataset-1.1.dist-info/LICENSE
DALI_dataset-1.1.dist-info/METADATA
DALI_dataset-1.1.dist-info/WHEEL
DALI_dataset-1.1.dist-info/top_level.txt
DALI_dataset-1.1.dist-info/RECORD
