Metadata-Version: 2.1
Name: DALI-dataset
Version: 1.1
Summary: Code for working with the DALI dataset
Home-page: http://github.com/gabolsgabs/DALI
Author: Gabriel Meseguer Brocal
Author-email: gabriel.meseguer.brocal@ircam.fr
License: afl-3.0
Platform: UNKNOWN
Requires-Dist: youtube-dl
